stache_ai/__init__.py
stache_ai/config.py
stache_ai/api/__init__.py
stache_ai/api/main.py
stache_ai/api/routes/__init__.py
stache_ai/api/routes/capture.py
stache_ai/api/routes/documents.py
stache_ai/api/routes/health.py
stache_ai/api/routes/insights.py
stache_ai/api/routes/models.py
stache_ai/api/routes/namespaces.py
stache_ai/api/routes/pending.py
stache_ai/api/routes/query.py
stache_ai/api/routes/upload.py
stache_ai/chunking/__init__.py
stache_ai/chunking/base.py
stache_ai/chunking/character.py
stache_ai/chunking/factory.py
stache_ai/chunking/hierarchical.py
stache_ai/chunking/markdown.py
stache_ai/chunking/recursive.py
stache_ai/chunking/semantic.py
stache_ai/chunking/transcript.py
stache_ai/chunking/strategies/__init__.py
stache_ai/cli/__init__.py
stache_ai/cli/__main__.py
stache_ai/cli/backfill_document_index.py
stache_ai/cli/dump_cmd.py
stache_ai/cli/import_cmd.py
stache_ai/cli/main.py
stache_ai/cli/migrate_cmd.py
stache_ai/cli/namespace_cmd.py
stache_ai/cli/providers_cmd.py
stache_ai/cli/redis_export.py
stache_ai/cli/vectors_cmd.py
stache_ai/core/__init__.py
stache_ai/core/operations.py
stache_ai/loaders/__init__.py
stache_ai/loaders/base.py
stache_ai/loaders/factory.py
stache_ai/loaders/pdf.py
stache_ai/loaders/text.py
stache_ai/middleware/__init__.py
stache_ai/middleware/base.py
stache_ai/middleware/chain.py
stache_ai/middleware/context.py
stache_ai/middleware/results.py
stache_ai/middleware/testing.py
stache_ai/models/__init__.py
stache_ai/models/insight.py
stache_ai/providers/__init__.py
stache_ai/providers/base.py
stache_ai/providers/factories.py
stache_ai/providers/plugin_loader.py
stache_ai/providers/document_index/__init__.py
stache_ai/providers/embeddings/__init__.py
stache_ai/providers/embeddings/fallback.py
stache_ai/providers/llm/__init__.py
stache_ai/providers/llm/fallback.py
stache_ai/providers/llm/none.py
stache_ai/providers/namespace/__init__.py
stache_ai/providers/namespace/sqlite.py
stache_ai/providers/reranker/__init__.py
stache_ai-0.1.2.dist-info/METADATA
stache_ai-0.1.2.dist-info/WHEEL
stache_ai-0.1.2.dist-info/entry_points.txt
stache_ai-0.1.2.dist-info/top_level.txt
stache_ai-0.1.2.dist-info/RECORD
