Metadata-Version: 2.4
Name: stache-ai
Version: 0.1.2
Summary: Personal AI-powered knowledge base with RAG
Author: Stache Contributors
License: MIT
Project-URL: Homepage, https://github.com/stache-ai/stache-ai
Project-URL: Documentation, https://github.com/stache-ai/stache#readme
Project-URL: Repository, https://github.com/stache-ai/stache-ai
Project-URL: Issues, https://github.com/stache-ai/stache/issues
Keywords: stache,rag,ai,knowledge-base,llm,vector-database,semantic-search
Classifier: Development Status :: 4 - Beta
Classifier: Intended Audience :: Developers
Classifier: License :: OSI Approved :: MIT License
Classifier: Operating System :: OS Independent
Classifier: Programming Language :: Python :: 3
Classifier: Programming Language :: Python :: 3.10
Classifier: Programming Language :: Python :: 3.11
Classifier: Programming Language :: Python :: 3.12
Classifier: Topic :: Scientific/Engineering :: Artificial Intelligence
Requires-Python: >=3.10
Requires-Dist: fastapi>=0.109.0
Requires-Dist: uvicorn[standard]>=0.27.0
Requires-Dist: python-multipart>=0.0.6
Requires-Dist: pypdf2>=3.0.1
Requires-Dist: pdfplumber>=0.10.3
Requires-Dist: markdown>=3.5.2
Requires-Dist: python-dotenv>=1.0.1
Requires-Dist: tiktoken>=0.5.2
Requires-Dist: pydantic>=2.7.0
Requires-Dist: pydantic-settings>=2.3.0
Requires-Dist: click>=8.1.7
Requires-Dist: rich>=13.7.0
Requires-Dist: tqdm>=4.66.1
Provides-Extra: dev
Requires-Dist: pytest>=7.0.0; extra == "dev"
Requires-Dist: pytest-asyncio>=0.21.0; extra == "dev"
Requires-Dist: pytest-cov>=4.0.0; extra == "dev"
Requires-Dist: httpx>=0.25.0; extra == "dev"
Requires-Dist: mypy>=1.0.0; extra == "dev"
Requires-Dist: ruff>=0.1.0; extra == "dev"
Provides-Extra: aws
Requires-Dist: stache-ai-s3vectors>=0.1.0; extra == "aws"
Requires-Dist: stache-ai-dynamodb>=0.1.0; extra == "aws"
Requires-Dist: stache-ai-bedrock>=0.1.0; extra == "aws"
Provides-Extra: ollama
Requires-Dist: stache-ai-ollama>=0.1.0; extra == "ollama"
Provides-Extra: openai
Requires-Dist: stache-ai-openai>=0.1.0; extra == "openai"
Provides-Extra: ocr
Requires-Dist: stache-ai-ocr>=0.1.0; extra == "ocr"
Provides-Extra: documents
Requires-Dist: stache-ai-documents>=0.1.0; extra == "documents"
Provides-Extra: all-loaders
Requires-Dist: stache-ai-ocr>=0.1.0; extra == "all-loaders"
Requires-Dist: stache-ai-documents>=0.1.0; extra == "all-loaders"
